Metadata-Version: 2.4
Name: packaging-demo-paulokj123
Version: 0.0.0
Summary: Lovely Spam! Wonderful Spam!
Author: Paul Addai
Author-email: pauljnraddai@yahoo.com
Maintainer-email: Brett Cannon <brett@python.org>
Project-URL: homepage, https://example.com
Project-URL: documentation, https://readthedocs.org
Project-URL: repository, https://github.com
Project-URL: changelog, https://github.com/me/spam/blob/master/CHANGELOG.md
Keywords: one,two
Classifier: Programming Language :: Python
Requires-Python: >=3.8
Requires-Dist: numpy
Requires-Dist: fastapi
Provides-Extra: test
Requires-Dist: pytest; extra == "test"
Requires-Dist: pytest-cov; extra == "test"
Provides-Extra: release
Requires-Dist: build; extra == "release"
Requires-Dist: twine; extra == "release"
Provides-Extra: static-code-qa
Requires-Dist: pre-commit; extra == "static-code-qa"
Provides-Extra: colors
Requires-Dist: rich; extra == "colors"
Provides-Extra: all
Requires-Dist: packaging-demo[colors,dev]; extra == "all"
Provides-Extra: dev
Requires-Dist: packaging-demo[release,static-code-qa,test]; extra == "dev"
